[
  {
    "dataset": "Wisconsin Breast Cancer",
    "n_features_total": 30,
    "model": "Random Forest",
    "selector": "Baseline (no FS)",
    "selector_family": "None",
    "k_ratio": 1.0,
    "n_selected_mean": 30.0,
    "accuracy_mean": 0.9525850023288308,
    "accuracy_std": 0.018008381071502738,
    "f1_mean": 0.9524315105983995,
    "f1_std": 0.018352134330549316,
    "train_time_s_mean": 0.2440868836005393,
    "total_time_s_mean": 0.27717424179936645,
    "energy_j_mean": 18.016325716958818,
    "energy_wh_mean": 0.00500453492137745
  },
  {
    "dataset": "Wisconsin Breast Cancer",
    "n_features_total": 30,
    "model": "Random Forest",
    "selector": "Filter (Mutual Info)",
    "selector_family": "Filter",
    "k_ratio": 0.75,
    "n_selected_mean": 22.0,
    "accuracy_mean": 0.9508150908244062,
    "accuracy_std": 0.016216320113834143,
    "f1_mean": 0.950637847003072,
    "f1_std": 0.01656820796689008,
    "train_time_s_mean": 0.18757139180015656,
    "total_time_s_mean": 0.30236655860062456,
    "energy_j_mean": 19.653826309040596,
    "energy_wh_mean": 0.005459396196955721
  },
  {
    "dataset": "Wisconsin Breast Cancer",
    "n_features_total": 30,
    "model": "Random Forest",
    "selector": "Wrapper (RFE)",
    "selector_family": "Wrapper",
    "k_ratio": 0.75,
    "n_selected_mean": 22.0,
    "accuracy_mean": 0.9595870206489675,
    "accuracy_std": 0.006971918072338138,
    "f1_mean": 0.9593957502326298,
    "f1_std": 0.007278121461709986,
    "train_time_s_mean": 0.18803297520062187,
    "total_time_s_mean": 0.23044256659995882,
    "energy_j_mean": 14.978766828997323,
    "energy_wh_mean": 0.004160768563610367
  },
  {
    "dataset": "Wisconsin Breast Cancer",
    "n_features_total": 30,
    "model": "Random Forest",
    "selector": "Embedded (L1-SVM)",
    "selector_family": "Embedded",
    "k_ratio": 0.75,
    "n_selected_mean": 22.0,
    "accuracy_mean": 0.9648657040832169,
    "accuracy_std": 0.005474508654284594,
    "f1_mean": 0.9648675008267219,
    "f1_std": 0.005362852992956537,
    "train_time_s_mean": 0.20912250020046486,
    "total_time_s_mean": 0.24490350839987512,
    "energy_j_mean": 15.918728045991884,
    "energy_wh_mean": 0.004421868901664412
  },
  {
    "dataset": "Wisconsin Breast Cancer",
    "n_features_total": 30,
    "model": "Random Forest",
    "selector": "Embedded (RF importance)",
    "selector_family": "Embedded",
    "k_ratio": 0.75,
    "n_selected_mean": 22.0,
    "accuracy_mean": 0.9560782487191428,
    "accuracy_std": 0.007777102123864983,
    "f1_mean": 0.9560072625656952,
    "f1_std": 0.007769751833621997,
    "train_time_s_mean": 0.18002555040002335,
    "total_time_s_mean": 0.38080052500008604,
    "energy_j_mean": 24.752034125005594,
    "energy_wh_mean": 0.006875565034723776
  }
]