[
  {
    "dataset": "Wisconsin Breast Cancer",
    "n_features_total": 30,
    "model": "Logistic Regression",
    "selector": "Baseline (no FS)",
    "selector_family": "None",
    "k_ratio": 1.0,
    "n_selected_mean": 30.0,
    "accuracy_mean": 0.9754230709517155,
    "accuracy_std": 0.014017644997030473,
    "f1_mean": 0.975232204372628,
    "f1_std": 0.014244255764840657,
    "train_time_s_mean": 0.0055581583997991405,
    "total_time_s_mean": 0.005842541599849938,
    "energy_j_mean": 0.37976520399024594,
    "energy_wh_mean": 0.00010549033444173499
  },
  {
    "dataset": "Wisconsin Breast Cancer",
    "n_features_total": 30,
    "model": "Logistic Regression",
    "selector": "Filter (Mutual Info)",
    "selector_family": "Filter",
    "k_ratio": 0.75,
    "n_selected_mean": 22.0,
    "accuracy_mean": 0.9789318428815401,
    "accuracy_std": 0.013114128316674255,
    "f1_mean": 0.9787662386776287,
    "f1_std": 0.013342801691536161,
    "train_time_s_mean": 0.0067449914007738695,
    "total_time_s_mean": 0.13708929999920655,
    "energy_j_mean": 8.910804499948426,
    "energy_wh_mean": 0.0024752234722078964
  },
  {
    "dataset": "Wisconsin Breast Cancer",
    "n_features_total": 30,
    "model": "Logistic Regression",
    "selector": "Wrapper (RFE)",
    "selector_family": "Wrapper",
    "k_ratio": 0.75,
    "n_selected_mean": 22.0,
    "accuracy_mean": 0.9754230709517155,
    "accuracy_std": 0.015075578675513112,
    "f1_mean": 0.9752095615778691,
    "f1_std": 0.015421316802531502,
    "train_time_s_mean": 0.0034055667994834947,
    "total_time_s_mean": 0.016327591799927176,
    "energy_j_mean": 1.0612934669952665,
    "energy_wh_mean": 0.00029480374083201846
  },
  {
    "dataset": "Wisconsin Breast Cancer",
    "n_features_total": 30,
    "model": "Logistic Regression",
    "selector": "Embedded (L1-SVM)",
    "selector_family": "Embedded",
    "k_ratio": 0.75,
    "n_selected_mean": 22.0,
    "accuracy_mean": 0.9806862288464524,
    "accuracy_std": 0.006539441283506109,
    "f1_mean": 0.9806482647794408,
    "f1_std": 0.0065672154163534495,
    "train_time_s_mean": 0.0032065751998743507,
    "total_time_s_mean": 0.009852174800471403,
    "energy_j_mean": 0.6403913620306412,
    "energy_wh_mean": 0.00017788648945295588
  },
  {
    "dataset": "Wisconsin Breast Cancer",
    "n_features_total": 30,
    "model": "Logistic Regression",
    "selector": "Embedded (RF importance)",
    "selector_family": "Embedded",
    "k_ratio": 0.75,
    "n_selected_mean": 22.0,
    "accuracy_mean": 0.9754230709517155,
    "accuracy_std": 0.011616237298934176,
    "f1_mean": 0.975280955412549,
    "f1_std": 0.011827411494055234,
    "train_time_s_mean": 0.0039024498000799213,
    "total_time_s_mean": 0.2205853417995968,
    "energy_j_mean": 14.338047216973791,
    "energy_wh_mean": 0.003982790893603831
  }
]